{
  "1997": [
    {
      "name": "第8届-银荔杯",
      "fullname": "1997年-第8届-银荔杯"
    },
    {
      "name": "第5届世界象棋锦标赛",
      "fullname": "1997年-第5届世界象棋锦标赛-(275局)"
    },
    {
      "name": "第05届世界象棋锦标赛",
      "fullname": "1997年-第05届世界象棋锦标赛"
    },
    {
      "name": "中国梁山第1届棋友杯全国象棋精英赛",
      "fullname": "1997年-05中国梁山第1届棋友杯全国象棋精英赛"
    },
    {
      "name": "第二届“广洋杯”全国象棋大棋圣赛",
      "fullname": "1997年-第二届“广洋杯”全国象棋大棋圣赛"
    },
    {
      "name": "中立杯",
      "fullname": "1997年-中立杯"
    },
    {
      "name": "第4届嘉丰房地产杯象棋王位赛",
      "fullname": "1997年-08第4届嘉丰房地产杯象棋王位赛"
    },
    {
      "name": "全国象棋个人锦标赛",
      "fullname": "1997年-10月07日全国象棋个人锦标赛"
    },
    {
      "name": "全国象棋团体赛男子组",
      "fullname": "1997年-全国象棋团体赛男子组"
    },
    {
      "name": "首届“林河杯”象棋名人赛对局集-(完整版41局)",
      "fullname": "1997年-首届“林河杯”象棋名人赛对局集-(完整版41局)"
    },
    {
      "name": "第17届五羊杯象棋赛",
      "fullname": "1997年-第17届五羊杯象棋赛"
    },
    {
      "name": "全国象棋团体赛女子组",
      "fullname": "1997年-全国象棋团体赛女子组"
    },
    {
      "name": "第8届“银荔杯”",
      "fullname": "1997年-04第8届“银荔杯”"
    },
    {
      "name": "第5届嘉宝杯",
      "fullname": "1997年-11第5届嘉宝杯"
    },
    {
      "name": "年东宝杯象棋对抗赛男子组",
      "fullname": "1997年-04年东宝杯象棋对抗赛男子组"
    },
    {
      "name": "年东宝杯象棋对抗赛女子组",
      "fullname": "1997年-04年东宝杯象棋对抗赛女子组"
    },
    {
      "name": "全国象棋团体赛乙组",
      "fullname": "1997年-全国象棋团体赛乙组"
    },
    {
      "name": "象棋赛对局选",
      "fullname": "1997年-象棋赛对局选"
    },
    {
      "name": "通州杯华东华南象棋对抗赛",
      "fullname": "1997年-05通州杯华东华南象棋对抗赛"
    }
  ]
}