{
	"meta": {
		"title": "Bộ sưu tập trung cuoc kinh dien",
		"description": "....",
		"updatedAt": "2025/02/20",
		"tags": ["cờ tướng", "giang hồ", "sát cục", "cờ tàn"]
	},
	"details": {
		"file1.dpxq": {
			"preview": "3199473949486999678899052646869964664241405060829902990324438499",
			"description": "description for file 1 (mid-games)"
		},
		"file2.dpxq": {
			"preview": "3167294849599999352047064686999914026041405099626632990423438399",
			"description": "description for file 2 (mid-games)"
		},
		"file3.dpxq": {
			"preview": "1307293949486967254799054666869910620230405060993112420343638399",
			"description": "description for file 3 (mid-games)"
		}
	}
}
